RemoteNowApiWrapper/__init__.py
RemoteNowApiWrapper/hisense.cert
RemoteNowApiWrapper/keys.py
RemoteNowApiWrapper-0.0.12.dist-info/LICENSE
RemoteNowApiWrapper-0.0.12.dist-info/METADATA
RemoteNowApiWrapper-0.0.12.dist-info/WHEEL
RemoteNowApiWrapper-0.0.12.dist-info/top_level.txt
RemoteNowApiWrapper-0.0.12.dist-info/RECORD
