Metadata-Version: 2.2
Name: RemoteNowApiWrapper
Version: 0.0.12
Summary: Wrapper for the RemoteNowApi
Home-page: https://github.com/Tabisch/RemoteNowApi
Author: Tabisch
Author-email: tobithieman@gmail.com
Project-URL: Bug Tracker, https://github.com/Tabisch/RemoteNowApi/issues
Classifier: Programming Language :: Python :: 3
Classifier: License :: OSI Approved :: MIT License
Classifier: Operating System :: OS Independent
Requires-Python: >=3.11
License-File: LICENSE
